awstracer/__init__.py
awstracer/_version.py
awstracer/player.py
awstracer/recorder.py
awstracer/tracer.py
awstracer/utils.py
awstracer-1.3.dist-info/LICENSE
awstracer-1.3.dist-info/METADATA
awstracer-1.3.dist-info/WHEEL
awstracer-1.3.dist-info/entry_points.txt
awstracer-1.3.dist-info/top_level.txt
awstracer-1.3.dist-info/RECORD
