Metadata-Version: 2.2
Name: awstracer
Version: 1.3
Summary: AWS cli trace recorder and player
Home-page: https://github.com/anvilsecure/awstracer
Author: Anvil Secure
Author-email: info@anvilsecure.com
Keywords: AWS awscli cli tracer recorder player utility
Classifier: Programming Language :: Python :: 3
Classifier: License :: OSI Approved :: MIT License
Classifier: Operating System :: OS Independent
Classifier: Operating System :: POSIX
Classifier: Operating System :: MacOS :: MacOS X
Classifier: Development Status :: 5 - Production/Stable
Classifier: Programming Language :: Python :: 3 :: Only
Classifier: Programming Language :: Python :: 3.6
Classifier: Programming Language :: Python :: 3.8
Classifier: Programming Language :: Python :: 3.9
Classifier: Programming Language :: Python :: 3.6
Classifier: Development Status :: 5 - Production/Stable
Classifier: Environment :: Console
Classifier: Intended Audience :: Developers
Classifier: Intended Audience :: Information Technology
Classifier: Intended Audience :: System Administrators
Requires-Python: >=3.6
License-File: LICENSE
Requires-Dist: awscli>=1.18.39
Requires-Dist: botocore>=1.15.39
Provides-Extra: test
Requires-Dist: tox; extra == "test"
Requires-Dist: flake8; extra == "test"
Dynamic: author
Dynamic: author-email
Dynamic: classifier
Dynamic: description
Dynamic: description-content-type
Dynamic: home-page
Dynamic: keywords
Dynamic: provides-extra
Dynamic: requires-dist
Dynamic: requires-python
Dynamic: summary
